{
	"configurations" : 
	[
		{
			"directories" : 
			[
				{
					"build" : ".",
					"childIndexes" : 
					[
						1
					],
					"jsonFile" : "directory-.-Debug-d0094a50bb2071803777.json",
					"minimumCMakeVersion" : 
					{
						"string" : "3.0"
					},
					"projectIndex" : 0,
					"source" : ".",
					"targetIndexes" : 
					[
						1
					]
				},
				{
					"build" : "src",
					"jsonFile" : "directory-src-Debug-c94b7c2814d5a21df52c.json",
					"minimumCMakeVersion" : 
					{
						"string" : "3.0"
					},
					"parentIndex" : 0,
					"projectIndex" : 0,
					"source" : "src",
					"targetIndexes" : 
					[
						0
					]
				}
			],
			"name" : "Debug",
			"projects" : 
			[
				{
					"directoryIndexes" : 
					[
						0,
						1
					],
					"name" : "myproject",
					"targetIndexes" : 
					[
						0,
						1
					]
				}
			],
			"targets" : 
			[
				{
					"directoryIndex" : 1,
					"id" : "MiniDNNLib::@145eef247bfb46b6828c",
					"jsonFile" : "target-MiniDNNLib-Debug-f236d63ac8e66467e334.json",
					"name" : "MiniDNNLib",
					"projectIndex" : 0
				},
				{
					"directoryIndex" : 0,
					"id" : "demo::@6890427a1f51a3e7e1df",
					"jsonFile" : "target-demo-Debug-9b04561840ae3766f6e7.json",
					"name" : "demo",
					"projectIndex" : 0
				}
			]
		}
	],
	"kind" : "codemodel",
	"paths" : 
	{
		"build" : "C:/HCMUS/4th/HKI/PP/Final/mini-dnn-cpp/build",
		"source" : "C:/HCMUS/4th/HKI/PP/Final/mini-dnn-cpp"
	},
	"version" : 
	{
		"major" : 2,
		"minor" : 6
	}
}
